threetotheonehalfpy/__init__.py
threetotheonehalfpy/calculate.py
threetotheonehalfpy-1.0.3.dist-info/LICENSE
threetotheonehalfpy-1.0.3.dist-info/METADATA
threetotheonehalfpy-1.0.3.dist-info/WHEEL
threetotheonehalfpy-1.0.3.dist-info/top_level.txt
threetotheonehalfpy-1.0.3.dist-info/RECORD
