Metadata-Version: 2.1
Name: threetotheonehalfpy
Version: 1.0.3
Summary: A Python package for rapid and secure calculation of three to the one half in an industrial environment
Home-page: https://github.com/funtrix-ds1/threetotheonehalfpy
Author: funtrix_doesstuff
License-File: LICENSE
